<?xml version="1.0" encoding="utf-8"?>
<!DOCTYPE cesAlign PUBLIC "-//CES//DTD XML cesAlign//EN" "">
<cesAlign version="1.0">
<linkGrp targType="s" fromDoc="zh_TW/2024/30326046_30241060_1_15/1958923333.xml.gz" toDoc="id/2024/30326046_30241060_1_15/1958426994.xml.gz">
<link xtargets="1;1" />
<link xtargets="3;2" />
<link xtargets="4;3" />
<link xtargets="5;4" />
<link xtargets="6;5" />
<link xtargets="7 8;6" />
<link xtargets="9 10 11;7 8 9" />
<link xtargets="12;10" />
<link xtargets="13;11" />
<link xtargets="14;12 13 14" />
<link xtargets="15;15 16 17" />
<link xtargets="16;18" />
<link xtargets="17;19" />
<link xtargets="18;20" />
<link xtargets="19;21 22" />
<link xtargets="20;23" />
<link xtargets="21;24" />
<link xtargets="22;25" />
<link xtargets="23;26" />
<link xtargets="24;27" />
<link xtargets="25;28" />
<link xtargets="27 28;30" />
<link xtargets="29;31" />
<link xtargets="30;32 33" />
<link xtargets="31;34" />
<link xtargets="32;35" />
<link xtargets="33;36" />
<link xtargets="34;37" />
<link xtargets="35;38" />
<link xtargets="36;39" />
<link xtargets="37;40" />
<link xtargets="38;41" />
<link xtargets="39;42" />
<link xtargets="40;43" />
<link xtargets="41 42;44 45 46" />
<link xtargets="43;47" />
<link xtargets="44;48" />
<link xtargets="45;49" />
<link xtargets="46;50" />
<link xtargets="47;51" />
<link xtargets="48 49;52" />
<link xtargets="50;53" />
<link xtargets="51;54" />
<link xtargets="52;55" />
<link xtargets="53;56" />
<link xtargets="54;57" />
<link xtargets="55 56;58 59" />
<link xtargets="57;60" />
<link xtargets="58;61" />
<link xtargets="59;62 63" />
<link xtargets="60;64" />
<link xtargets="61;65" />
<link xtargets="62;66" />
<link xtargets="63;67" />
<link xtargets="64;68 69" />
<link xtargets="65;70" />
<link xtargets="66;71" />
<link xtargets="67 68;72 73" />
<link xtargets="69 70;74 75" />
<link xtargets="71;76" />
<link xtargets="72;77" />
<link xtargets="73;78" />
<link xtargets="74;79" />
<link xtargets="75;80" />
<link xtargets="76;81" />
<link xtargets="77 78;82 83 84 85" />
<link xtargets="79;86 87 88" />
<link xtargets="80;90 91 92" />
<link xtargets="81;94" />
<link xtargets="82;95" />
<link xtargets="83;96" />
<link xtargets="84;97" />
<link xtargets="85;98" />
<link xtargets="86 87;99" />
<link xtargets="88;100" />
<link xtargets="89;101" />
<link xtargets="90;102" />
<link xtargets="91;103" />
<link xtargets="92;104" />
<link xtargets="93;105" />
<link xtargets="94;106" />
<link xtargets="95;107" />
<link xtargets="96;108" />
<link xtargets="97;109" />
<link xtargets="98;110" />
<link xtargets="99 100 101;111 112" />
<link xtargets="102 103;113" />
<link xtargets="104;114 115" />
<link xtargets="105;116" />
<link xtargets="106;117" />
<link xtargets="107;118" />
<link xtargets="108;119" />
<link xtargets="109;120" />
<link xtargets="110;121" />
<link xtargets="111;122" />
<link xtargets="112;123" />
<link xtargets="113;124" />
<link xtargets="114;125" />
<link xtargets="115;126" />
<link xtargets="116;127" />
<link xtargets="117;128" />
<link xtargets="118;129" />
<link xtargets="119;130 131" />
<link xtargets="120;132" />
<link xtargets="121;133" />
<link xtargets="122 123;134 135" />
<link xtargets="124;136" />
<link xtargets="125;137" />
<link xtargets="126;138" />
<link xtargets="127;139" />
<link xtargets="128 129 130;140 141" />
<link xtargets="131;142 143" />
<link xtargets="132 133;144" />
<link xtargets="134;145" />
<link xtargets="135 136 137 138;147 148" />
<link xtargets="139;149 150" />
<link xtargets="140;151" />
<link xtargets="141;152" />
<link xtargets="142;153 154" />
<link xtargets="143;155" />
<link xtargets="144;156 157" />
<link xtargets="145;158" />
<link xtargets="146;159" />
<link xtargets="147;160" />
<link xtargets="148;161" />
<link xtargets="149;162" />
<link xtargets="150;163" />
<link xtargets="151 152 153;164 165" />
<link xtargets="154;166" />
<link xtargets="155;167" />
<link xtargets="156;168" />
<link xtargets="157;169" />
<link xtargets="158;170" />
<link xtargets="159;171" />
<link xtargets="160;172" />
<link xtargets="161;173" />
<link xtargets="162;174" />
<link xtargets="163;175" />
<link xtargets="164;176 177" />
<link xtargets="165;178" />
<link xtargets="166;179" />
<link xtargets="167;180" />
<link xtargets="168 169;181" />
<link xtargets="170;182" />
<link xtargets="171;183" />
<link xtargets="172 173;184" />
<link xtargets="174;186" />
<link xtargets="175;187" />
<link xtargets="176;188" />
<link xtargets="177 178 179 180;189 190 191 192" />
<link xtargets="181;193 194" />
<link xtargets="182 183 184;195 196 197" />
<link xtargets="185;198" />
<link xtargets="186;199" />
<link xtargets="187 188;200 201 202 203" />
<link xtargets="189 190 191;204 205 206" />
<link xtargets="192;207" />
<link xtargets="193 194;208 209 210" />
<link xtargets="195;211" />
<link xtargets="196;212" />
<link xtargets="197;213" />
<link xtargets="198;214" />
<link xtargets="199;215" />
<link xtargets="200;216" />
<link xtargets="201;217" />
<link xtargets="202;218" />
<link xtargets="203 204;219 220 221" />
<link xtargets="205;222" />
<link xtargets="206;223" />
<link xtargets="207;224" />
<link xtargets="208;225" />
<link xtargets="209;226" />
<link xtargets="210;227" />
<link xtargets="211;228" />
<link xtargets="212;229" />
<link xtargets="213 214;230 231" />
<link xtargets="215 216;232 233" />
<link xtargets="217;234" />
<link xtargets="218;235" />
<link xtargets="219;236" />
<link xtargets="220;237" />
<link xtargets="221;238" />
<link xtargets="222;239" />
<link xtargets="223 224;240 241" />
<link xtargets="225;242" />
<link xtargets="226 227;243 244" />
<link xtargets="228 229;245 246" />
<link xtargets="230;247" />
<link xtargets="231;248" />
<link xtargets="232;249" />
<link xtargets="233;250 251 252" />
<link xtargets="234;253" />
<link xtargets="235;254" />
<link xtargets="236;255" />
<link xtargets="237;256 257" />
<link xtargets="238;258" />
<link xtargets="239;259" />
<link xtargets="240 241;260 261 262" />
<link xtargets="242;263" />
<link xtargets="243 244;264 265" />
<link xtargets="245;266" />
<link xtargets="246;267" />
<link xtargets="247;268" />
<link xtargets="248 249;269" />
<link xtargets="250;270" />
<link xtargets="251;271" />
<link xtargets="252 253;272 273" />
<link xtargets="254;274" />
<link xtargets="255;275" />
<link xtargets="256;276" />
<link xtargets="257;277" />
<link xtargets="258 259;278" />
<link xtargets="260;279" />
<link xtargets="261 262;280 281" />
<link xtargets="263;282" />
<link xtargets="264;283" />
<link xtargets="265;284" />
<link xtargets="266;285" />
<link xtargets="267;286" />
<link xtargets="268;287" />
<link xtargets="269;288" />
<link xtargets="270;289" />
<link xtargets="271 272;290 291" />
<link xtargets="273;292" />
<link xtargets="274;293" />
<link xtargets="275;294" />
<link xtargets="276;295" />
<link xtargets="277;296" />
<link xtargets="278;297" />
<link xtargets="279;298" />
<link xtargets="280;299" />
<link xtargets="281;300" />
<link xtargets="282;301" />
<link xtargets="283;302" />
<link xtargets="284 285;303" />
<link xtargets="286 287 288;304 305" />
<link xtargets="289;306" />
<link xtargets="290;307" />
<link xtargets="291;308" />
<link xtargets="292;309" />
<link xtargets="293;310" />
<link xtargets="294 295;311" />
<link xtargets="296;312" />
<link xtargets="297;313" />
<link xtargets="298;314" />
<link xtargets="299;315" />
<link xtargets="300;316" />
<link xtargets="301;317 318" />
<link xtargets="302;319" />
<link xtargets="303;320" />
<link xtargets="304;321" />
<link xtargets="305;322" />
<link xtargets="307;324" />
<link xtargets="308;325 326" />
<link xtargets="309;327" />
<link xtargets="310;328" />
<link xtargets="311;329" />
<link xtargets="312;330" />
<link xtargets="313;331" />
<link xtargets="314;332" />
<link xtargets="315 316;333" />
<link xtargets="317;334" />
<link xtargets="318 319 320;335 336 337 338 339" />
<link xtargets="322;341" />
<link xtargets="323;342" />
<link xtargets="324 325;343" />
<link xtargets="326;344 345" />
<link xtargets="327 328;346" />
<link xtargets="329;347" />
<link xtargets="330;348" />
<link xtargets="331 332;349" />
<link xtargets="333 334;350 351" />
<link xtargets="335;352" />
<link xtargets="336 337;353" />
<link xtargets="338 339 340;354" />
<link xtargets="341;355" />
<link xtargets="342;356" />
<link xtargets="343;357 358" />
<link xtargets="344;359" />
<link xtargets="345;360" />
<link xtargets="346;361" />
<link xtargets="347;362" />
<link xtargets="348;363" />
<link xtargets="349;364" />
<link xtargets="350;365" />
<link xtargets="351 352;366" />
<link xtargets="353 354;367" />
<link xtargets="355;368" />
<link xtargets="356;369 370" />
<link xtargets="357;371" />
<link xtargets="358;372" />
<link xtargets="359 360;373" />
<link xtargets="361;374 375" />
<link xtargets="362;376" />
<link xtargets="363;377" />
<link xtargets="364;378" />
<link xtargets="365;379" />
<link xtargets="366;380" />
<link xtargets="367;381" />
<link xtargets="368;382" />
<link xtargets="369;383" />
<link xtargets="370;384" />
<link xtargets="371 372;385 386" />
<link xtargets="373 374;387" />
<link xtargets="375;388" />
<link xtargets="376;389 390" />
<link xtargets="377 378;391 392" />
<link xtargets="379 380 381;393 394" />
<link xtargets="382;395" />
<link xtargets="383;396" />
<link xtargets="384;397" />
<link xtargets="385;398 399" />
<link xtargets="386;400" />
<link xtargets="387;401" />
<link xtargets="388 389;402" />
<link xtargets="390;403" />
<link xtargets="391;404" />
<link xtargets="393;406" />
<link xtargets="394;407" />
<link xtargets="395;408" />
<link xtargets="396;409" />
<link xtargets="397;410" />
<link xtargets="398;411" />
<link xtargets="399;412" />
<link xtargets="400;413 414" />
<link xtargets="401;415" />
<link xtargets="402;416" />
<link xtargets="403;417" />
<link xtargets="404;418" />
<link xtargets="405;419" />
<link xtargets="406 407;420 421" />
<link xtargets="408 409;422" />
<link xtargets="410;423" />
<link xtargets="411;424 425" />
<link xtargets="412 413;426" />
<link xtargets="414;427" />
<link xtargets="415;428" />
<link xtargets="416;429" />
<link xtargets="417;430" />
<link xtargets="418;431" />
<link xtargets="419;432" />
<link xtargets="420 421;433 434" />
<link xtargets="422;435" />
<link xtargets="423;436 437" />
<link xtargets="424;438" />
<link xtargets="425 426;439 440" />
<link xtargets="427;441" />
<link xtargets="428;442" />
<link xtargets="429 430;443 444" />
<link xtargets="431;445" />
<link xtargets="432;446" />
<link xtargets="433;447" />
<link xtargets="434;448" />
<link xtargets="435;449" />
<link xtargets="436 437;450" />
<link xtargets="438;451" />
<link xtargets="439;452" />
<link xtargets="440;453 454" />
<link xtargets="441;455" />
<link xtargets="442;456" />
<link xtargets="443;457" />
<link xtargets="444;458" />
<link xtargets="445;459" />
<link xtargets="446;460" />
<link xtargets="447;461" />
<link xtargets="448;462" />
<link xtargets="449;463" />
<link xtargets="450;464" />
<link xtargets="451 452 453;465 466" />
<link xtargets="454;467" />
<link xtargets="455;468" />
<link xtargets="456;469" />
<link xtargets="457;470" />
<link xtargets="458;471" />
<link xtargets="459;472" />
<link xtargets="460;473" />
<link xtargets="461 462;474 475" />
<link xtargets="463;476" />
<link xtargets="464;477" />
<link xtargets="465;478" />
<link xtargets="466;479" />
<link xtargets="467;480" />
<link xtargets="468;481" />
<link xtargets="469;482" />
<link xtargets="470;483" />
<link xtargets="471;484" />
<link xtargets="472;485" />
<link xtargets="473 474;486 487" />
<link xtargets="475;488" />
<link xtargets="476;489" />
<link xtargets="477 478;490 491" />
<link xtargets="479;492" />
<link xtargets="480;493" />
<link xtargets="481;494" />
<link xtargets="482 483;495 496" />
<link xtargets="484;497 498" />
<link xtargets="485;499" />
<link xtargets="486;500" />
<link xtargets="487;501" />
<link xtargets="488;502" />
<link xtargets="489;503" />
<link xtargets="490 491;504 505" />
<link xtargets="492;506" />
<link xtargets="493;507" />
<link xtargets="494;508" />
<link xtargets="495;509" />
<link xtargets="496;510" />
<link xtargets="497;511" />
<link xtargets="498;512" />
<link xtargets="499 500;513 514" />
<link xtargets="501;515" />
<link xtargets="502;516" />
<link xtargets="503;517" />
<link xtargets="504;518" />
<link xtargets="505;519" />
<link xtargets="506;520" />
<link xtargets="507;521" />
<link xtargets="508;522" />
<link xtargets="509;523" />
<link xtargets="510;524" />
<link xtargets="511;525" />
<link xtargets="512;526" />
<link xtargets="513 514 515;527 528" />
<link xtargets="516;529" />
<link xtargets="517 518;530" />
<link xtargets="519;531" />
<link xtargets="520;532" />
<link xtargets="521;533" />
<link xtargets="522;534" />
<link xtargets="523;535" />
<link xtargets="524;536" />
<link xtargets="525 526;537 538" />
<link xtargets="527;539" />
<link xtargets="528;540" />
<link xtargets="529;541" />
<link xtargets="530;542" />
<link xtargets="531;543" />
<link xtargets="532;544" />
<link xtargets="533;545" />
<link xtargets="534;546" />
<link xtargets="535;547" />
<link xtargets="536 537;548 549" />
<link xtargets="538;550" />
<link xtargets="539 540 541;551 552 553" />
<link xtargets="542;554" />
<link xtargets="543;555" />
<link xtargets="544;556" />
<link xtargets="545 546;557" />
<link xtargets="547;558" />
<link xtargets="548 549 550;559 560 561" />
<link xtargets="551;562" />
<link xtargets="552;563" />
<link xtargets="553;564" />
<link xtargets="554;565" />
<link xtargets="555;566" />
<link xtargets="556;567" />
<link xtargets="557;568" />
<link xtargets="558;569" />
<link xtargets="559 560;570" />
<link xtargets="561 562;571" />
<link xtargets="563;572" />
<link xtargets="564;573" />
<link xtargets="565;574" />
<link xtargets="566;575" />
<link xtargets="567;576" />
<link xtargets="568;577" />
<link xtargets="569;578" />
<link xtargets="570;579" />
<link xtargets="571;580" />
<link xtargets="572;581" />
<link xtargets="573;582" />
<link xtargets="574;583" />
<link xtargets="575;584" />
<link xtargets="576;585" />
<link xtargets="577;586" />
<link xtargets="578;587" />
<link xtargets="579;588" />
<link xtargets="580 581;589 590" />
<link xtargets="582;591 592" />
<link xtargets="583;593" />
<link xtargets="584;594" />
<link xtargets="585;595" />
<link xtargets="586;596" />
<link xtargets="587;597" />
<link xtargets="588;598" />
<link xtargets="589;599" />
<link xtargets="590;600" />
<link xtargets="591;601" />
<link xtargets="592;602" />
<link xtargets="593;603" />
<link xtargets="594 595;604 605" />
<link xtargets="599;609" />
<link xtargets="600;610" />
<link xtargets="601;611" />
<link xtargets="603 604;613 614" />
<link xtargets="605;615" />
<link xtargets="606;616" />
<link xtargets="607;617" />
<link xtargets="608;618" />
<link xtargets="609;619" />
<link xtargets="610 611 612 613 614;620 621 622 623" />
<link xtargets="615;624" />
<link xtargets="616;625 626" />
<link xtargets="617;627" />
<link xtargets="618 619;628 629" />
<link xtargets="620;630" />
<link xtargets="621;631" />
<link xtargets="622;632" />
<link xtargets="623;633" />
<link xtargets="624 625;634 635" />
<link xtargets="626;636" />
<link xtargets="627 628;637" />
<link xtargets="629 630;638" />
<link xtargets="631;639" />
<link xtargets="632;640" />
<link xtargets="633;641" />
<link xtargets="634;642" />
<link xtargets="635;643" />
<link xtargets="636 637;644 645" />
<link xtargets="638;646" />
<link xtargets="643;650" />
<link xtargets="644;651" />
<link xtargets="645;652" />
<link xtargets="646;653" />
<link xtargets="647;654" />
<link xtargets="648;655" />
<link xtargets="649;656" />
<link xtargets="650;657" />
<link xtargets="651;658" />
<link xtargets="652;659" />
<link xtargets="653 654 655;660 661 662" />
<link xtargets="656;663" />
<link xtargets="657;664" />
<link xtargets="658;665" />
<link xtargets="659;666" />
<link xtargets="660;667 668" />
<link xtargets="661;669" />
<link xtargets="662;670" />
<link xtargets="663;671" />
<link xtargets="664;672" />
<link xtargets="665;673" />
<link xtargets="666;674 675" />
<link xtargets="667;676" />
<link xtargets="668;677 678" />
<link xtargets="669;679" />
<link xtargets="670;680 681" />
<link xtargets="671;682" />
<link xtargets="672;683" />
<link xtargets="673;684" />
<link xtargets="674 675 676;685" />
<link xtargets="677 678;686" />
<link xtargets="679 680;687" />
<link xtargets="681 682;688" />
<link xtargets="683;689" />
<link xtargets="684;690" />
<link xtargets="685;691" />
<link xtargets="686;692" />
<link xtargets="687;693 694" />
<link xtargets="688;695" />
<link xtargets="689;696" />
<link xtargets="690;697 698 699" />
<link xtargets="691 692;700" />
<link xtargets="693;701" />
<link xtargets="694 695 696 697;702 703 704" />
<link xtargets="698;705" />
<link xtargets="699 700;706 707" />
<link xtargets="701;708" />
<link xtargets="702 703;709 710" />
<link xtargets="704;711" />
<link xtargets="705;712" />
<link xtargets="706;713" />
<link xtargets="707;714" />
<link xtargets="708;715" />
<link xtargets="709;716 717" />
<link xtargets="710 711;718" />
<link xtargets="712;719" />
<link xtargets="713 714;720 721" />
<link xtargets="715;722" />
<link xtargets="716;723 724" />
<link xtargets="717 718;725 726" />
<link xtargets="719 720;727" />
<link xtargets="721;728" />
<link xtargets="722 723;729" />
<link xtargets="724;730" />
<link xtargets="725;731" />
<link xtargets="726 727;732 733" />
<link xtargets="728;734" />
<link xtargets="729;735" />
<link xtargets="730;736" />
<link xtargets="731;737 738" />
<link xtargets="732;739" />
<link xtargets="733;740" />
<link xtargets="734;741" />
<link xtargets="735;742" />
<link xtargets="736;743" />
<link xtargets="737;744" />
<link xtargets="738;745" />
<link xtargets="739;746" />
<link xtargets="740;747" />
<link xtargets="741;748" />
<link xtargets="742;749 750" />
<link xtargets="743;751" />
<link xtargets="744;752" />
<link xtargets="745;753" />
<link xtargets="746;754" />
<link xtargets="747;755" />
<link xtargets="748;756" />
<link xtargets="749 750;757 758" />
<link xtargets="751;759" />
<link xtargets="752;760" />
</linkGrp>
</cesAlign>
